hanzo_memory/__init__.py
hanzo_memory/cli.py
hanzo_memory/config.py
hanzo_memory/server.py
hanzo_memory/api/__init__.py
hanzo_memory/api/auth.py
hanzo_memory/db/__init__.py
hanzo_memory/db/base.py
hanzo_memory/db/client.py
hanzo_memory/db/factory.py
hanzo_memory/db/lancedb_client.py
hanzo_memory/db/mock_infinity.py
hanzo_memory/mcp/__init__.py
hanzo_memory/mcp/__main__.py
hanzo_memory/mcp/server.py
hanzo_memory/models/__init__.py
hanzo_memory/models/base.py
hanzo_memory/models/chat.py
hanzo_memory/models/knowledge.py
hanzo_memory/models/memory.py
hanzo_memory/models/project.py
hanzo_memory/services/__init__.py
hanzo_memory/services/embeddings.py
hanzo_memory/services/embeddings_lancedb.py
hanzo_memory/services/llm.py
hanzo_memory/services/memory.py
hanzo_memory-1.0.0.dist-info/licenses/LICENSE
hanzo_memory-1.0.0.dist-info/METADATA
hanzo_memory-1.0.0.dist-info/WHEEL
hanzo_memory-1.0.0.dist-info/entry_points.txt
hanzo_memory-1.0.0.dist-info/top_level.txt
hanzo_memory-1.0.0.dist-info/RECORD
