Metadata-Version: 2.4
Name: hanzo-memory
Version: 1.0.0
Summary: AI memory service with FastAPI and MCP support
Author-email: "Hanzo Industries Inc." <dev@hanzo.ai>
License: BSD
Project-URL: Homepage, https://github.com/hanzoai/memory
Project-URL: Documentation, https://docs.hanzo.ai/memory
Project-URL: Repository, https://github.com/hanzoai/memory
Project-URL: Issues, https://github.com/hanzoai/memory/issues
Keywords: ai,memory,mcp,fastapi,embeddings
Classifier: Development Status :: 4 - Beta
Classifier: Intended Audience :: Developers
Classifier: License :: OSI Approved :: BSD License
Classifier: Programming Language :: Python :: 3
Classifier: Programming Language :: Python :: 3.13
Requires-Python: >=3.13
License-File: LICENSE
Requires-Dist: fastapi>=0.115.0
Requires-Dist: uvicorn[standard]>=0.32.0
Requires-Dist: pydantic>=2.9.0
Requires-Dist: pydantic-settings>=2.6.0
Requires-Dist: fastembed>=0.4.0
Requires-Dist: litellm>=1.56.0
Requires-Dist: httpx>=0.28.0
Requires-Dist: python-multipart>=0.0.12
Requires-Dist: python-jose[cryptography]>=3.3.0
Requires-Dist: passlib[bcrypt]>=1.7.0
Requires-Dist: redis>=5.2.0
Requires-Dist: orjson>=3.10.0
Requires-Dist: mcp>=1.2.0
Requires-Dist: structlog>=24.4.0
Requires-Dist: rich>=13.9.0
Requires-Dist: tiktoken>=0.8.0
Requires-Dist: tenacity>=9.0.0
Requires-Dist: aiocache>=0.12.0
Requires-Dist: numpy>=1.26.0
Requires-Dist: scikit-learn>=1.5.0
Requires-Dist: polars>=1.15.0
Requires-Dist: chromadb>=0.5.0
Requires-Dist: lancedb>=0.8.0
Requires-Dist: sentence-transformers>=5.0.0
Provides-Extra: dev
Requires-Dist: pytest>=8.3.0; extra == "dev"
Requires-Dist: pytest-asyncio>=0.24.0; extra == "dev"
Requires-Dist: pytest-cov>=6.0.0; extra == "dev"
Requires-Dist: ruff>=0.8.0; extra == "dev"
Requires-Dist: mypy>=1.13.0; extra == "dev"
Requires-Dist: black>=24.10.0; extra == "dev"
Requires-Dist: pre-commit>=4.0.0; extra == "dev"
Requires-Dist: ipython>=8.29.0; extra == "dev"
Requires-Dist: ipdb>=0.13.0; extra == "dev"
Requires-Dist: twine>=4.0.0; extra == "dev"
Provides-Extra: test
Requires-Dist: pytest>=8.3.0; extra == "test"
Requires-Dist: pytest-asyncio>=0.24.0; extra == "test"
Requires-Dist: pytest-cov>=6.0.0; extra == "test"
Requires-Dist: pytest-mock>=3.14.0; extra == "test"
Requires-Dist: faker>=30.0.0; extra == "test"
Requires-Dist: factory-boy>=3.3.0; extra == "test"
Requires-Dist: respx>=0.21.0; extra == "test"
Provides-Extra: docs
Requires-Dist: mkdocs>=1.6.0; extra == "docs"
Requires-Dist: mkdocs-material>=9.5.0; extra == "docs"
Requires-Dist: mkdocstrings[python]>=0.27.0; extra == "docs"
Dynamic: license-file
